MANIFEST.in
setup.py
scripts/pypi/automium_web.bat
scripts/pypi/automium_web_pypi.py
src/automium_web.py
src/automium_web.wsgi
src/automium_web.egg-info/PKG-INFO
src/automium_web.egg-info/SOURCES.txt
src/automium_web.egg-info/dependency_links.txt
src/automium_web.egg-info/not-zip-safe
src/automium_web.egg-info/requires.txt
src/automium_web.egg-info/top_level.txt
src/models/__init__.py
src/models/base.py
src/models/build.py
src/models/log.py
src/models/project.py
src/projects/README.md
src/quorum/__init__.py
src/quorum/acl.py
src/quorum/base.py
src/quorum/config.py
src/quorum/daemon.py
src/quorum/error.py
src/quorum/exceptions.py
src/quorum/execution.py
src/quorum/export.py
src/quorum/extras.py
src/quorum/jsonf.py
src/quorum/mail.py
src/quorum/model.py
src/quorum/mongodb.py
src/quorum/redisdb.py
src/quorum/request.py
src/quorum/session.py
src/quorum/typesf.py
src/quorum/util.py
src/quorum/validation.py
src/static/css/layout.css
src/static/images/favicon.ico
src/static/js/main.js
src/static/libs/layout/.git
src/static/libs/layout/.project
src/static/libs/layout/.settings/org.eclipse.core.resources.prefs
src/static/libs/layout/css/layout.css
src/static/libs/layout/images/check-button.png
src/static/libs/layout/images/separator-horizontal.png
src/static/libs/layout/js/layout.js
src/static/libs/uxf/.git
src/static/libs/uxf/css/ux-min.css
src/static/libs/uxf/css/ux-min.css.gz
src/static/libs/uxf/css/ux.css
src/static/libs/uxf/images/ux-logo.png
src/static/libs/uxf/images/ux.ico
src/static/libs/uxf/js/ux-min.js
src/static/libs/uxf/js/ux-min.js.gz
src/static/libs/uxf/js/ux.js
src/static/libs/uxf/styles/base/css/ux-min.css
src/static/libs/uxf/styles/base/css/ux-min.css.gz
src/static/libs/uxf/styles/base/css/ux.css
src/static/libs/uxf/styles/omni/css/ux-min.css
src/static/libs/uxf/styles/omni/css/ux-min.css.gz
src/static/libs/uxf/styles/omni/css/ux.css
src/static/libs/uxf/styles/omni/images/banner-blue.png
src/static/libs/uxf/styles/omni/images/banner-green.png
src/static/libs/uxf/styles/omni/images/banner-red.png
src/static/libs/uxf/styles/omni/images/banner-yellow.png
src/static/libs/uxf/styles/omni/images/breadcrumbs-arrow.png
src/static/libs/uxf/styles/omni/images/button-blue.png
