Metadata-Version: 1.0
Name: automium-web
Version: 0.1.1
Summary: Automium System Web Interface
Home-page: http://automium.com
Author: Hive Solutions Lda.
Author-email: development@hive.pt
License: GNU General Public License (GPL), Version 3
Keywords: automium build automation
Platform: UNKNOWN
Classifier: Development Status :: 3 - Alpha
Classifier: Topic :: Utilities
Classifier: License :: OSI Approved :: GNU General Public License (GPL)
Classifier: Operating System :: OS Independent
Classifier: Programming Language :: Python
Classifier: Programming Language :: Python :: 2.6
Classifier: Programming Language :: Python :: 2.7
